FLIM_fit/FLIM_GAN_9_27.h5
FLIM_fit/GUI.py
FLIM_fit/__init__.py
FLIM_fit-1.6.2.dist-info/METADATA
FLIM_fit-1.6.2.dist-info/WHEEL
FLIM_fit-1.6.2.dist-info/entry_points.txt
FLIM_fit-1.6.2.dist-info/top_level.txt
FLIM_fit-1.6.2.dist-info/RECORD
