Metadata-Version: 2.1
Name: FLIM-fit
Version: 1.6.2
Summary: This GUI performs fluorescence lifetime decay analysis at cellular level.
Home-page: UNKNOWN
Author: Linghao Hu
Author-email: hulinghao@tamu.edu
License: Walsh Lab
Keywords: Fluorescence Lifetime,Decay Analysis,Cell-Level
Platform: UNKNOWN
Classifier: Development Status :: 3 - Alpha
Classifier: Intended Audience :: Developers
Classifier: Topic :: Software Development :: Build Tools
Classifier: License :: OSI Approved :: BSD License
Classifier: Programming Language :: Python :: 3
Requires-Dist: customtkinter
Requires-Dist: numpy
Requires-Dist: pandas
Requires-Dist: scikit-learn
Requires-Dist: CTkMessagebox
Requires-Dist: scipy
Requires-Dist: matplotlib
Requires-Dist: tifffile
Requires-Dist: tensorflow
Requires-Dist: openpyxl
Requires-Dist: sdtfile
